Lectures/lec12/dff.v
`timescale 1ns/1ns

module dff( output logic q, input logic d, clk);
    always_ff @(posedge clk) begin
        q <= #2 d;
    end
endmodule

Lectures/lec12/tb_dff.v
`timescale 1ns/1ns

// parameter delay = 2;
module main;
    logic q, qbar, d, clk;

    //d_latch_gate d_latch(q, qbar, d, clk);
    //d_latch_behavior test_d_latch(q, qbar, d, clk);
    dff test_d_ff(q, d, clk);

    initial begin
        $monitor("t=%04d q=%b d=%b clk=%b",
            $time, q, d, clk); 
    end 

    initial begin
    $dumpfile("dff.vcd");
    $dumpvars(0, main);
        d = 0; clk = 0; #5;
        d = 0; clk = 1; #5;
        d = 0; clk = 0; #5;
        d = 1; clk = 0; #5;
        d = 1; clk = 1; #5;
        d = 1; clk = 0; #5;
        d = 0; clk = 0; #5;
        d = 0; clk = 1; #5;
        d = 1; clk = 1; #5;
        d = 0; clk = 1; #5;
        $finish;
    end
endmodule

Lectures/lec12/dff.vcd
$date
	Fri Feb  2 14:07:48 2024
$end
$version
	Icarus Verilog
$end
$timescale
	1ns
$end
$scope module main $end
$var wire 1 ! q $end
$var reg 1 " clk $end
$var reg 1 # d $end
$scope module test_d_ff $end
$var wire 1 " clk $end
$var wire 1 # d $end
$var reg 1 ! q $end
$upscope $end
$upscope $end
$enddefinitions $end
#0
$dumpvars
0#
0"
x!
$end
#5
1"
#7
0!
#10
0"
#15
1#
#20
1"
#22
1!
#25
0"
#30
0#
#35
1"
#37
0!
#40
1#
#45
0#
