Lectures/lecture_latches_ff/examples/rs.v
//https://www.xilinx.com/support/documentation/university/Vivado-Teaching/HDL-Design/2013x/Nexys4/Verilog/docs-pdf/lab5.pdf
`timescale 1ns / 1ns  // define the time units

module RS(input r, s, output q, qb);
	wire qi, qbi;
	
	assign #2 qi = q;
	assign #2 qbi = qb;
	assign #2 q = ~(r | qb);
	assign #2 qb = ~(s | q);
	
endmodule

module SR_latch_dataflow (input R, input S, output Q, output Qbar);
    assign #2 Q_i = Q;
    assign #2 Qbar_i = Qbar;
    assign #2 Q = ~ (R | Qbar);
    assign #2 Qbar = ~ (S | Q);
endmodule 

module SR_latch_gate (input R, input S, output Q, output Qbar);
nor (Q, R, Qbar);
nor (Qbar, S, Q);
endmodule 

module main;
	logic q, qb, r, s;
	SR_latch_gate testing(r, s, q, qb);
//	SR_latch_dataflow testing(r, s, q, qb);
//	RS testing(r, s, q, qb);
	integer all_inputs, i;
	
	assign {r,s} = all_inputs[1:0];
	initial begin
		$dumpfile("test.vcd");
		$dumpvars(0, main);
		i = 0;
		repeat( 8 ) begin
    		$display("t=%04d r=%b s=%b q=%b qb=%b", $time, r, s, q, qb  );
			all_inputs = i;
			#5;
		    i = i + 1;
		end
		$display("t=%04d r=%b s=%b", $time, r, s);
		$finish;
	end
endmodule

Lectures/lecture_latches_ff/examples/test.vcd
$date
	Tue Jul  7 10:54:35 2020
$end
$version
	Icarus Verilog
$end
$timescale
	1ns
$end
$scope module main $end
$var wire 1 ! s $end
$var wire 1 " r $end
$var wire 1 # qb $end
$var wire 1 $ q $end
$var integer 32 % all_inputs [31:0] $end
$var integer 32 & i [31:0] $end
$scope module testing $end
$var wire 1 $ Q $end
$var wire 1 # Qbar $end
$var wire 1 " R $end
$var wire 1 ! S $end
$upscope $end
$upscope $end
$enddefinitions $end
#0
$dumpvars
b0 &
b0 %
x$
x#
0"
0!
$end
#5
1$
0#
1!
b1 %
b1 &
#10
1#
0$
0!
1"
b10 %
b10 &
#15
0#
1!
b11 %
b11 &
#20
1$
0!
0"
b100 %
b100 &
#25
1!
b101 %
b101 &
#30
1#
0$
0!
1"
b110 %
b110 &
#35
0#
1!
b111 %
b111 &
#40
b1000 &
