Lectures/lec10/bitwise_and.v
`timescale 1ns/1ns

module bitwise_and(output logic [3:0] y, input logic [3:0] a, b);

    assign y = a&b;

endmodule

module main;
    logic [3:0] A, B, Y;
    
    bitwise_and dut(Y, A, B);
    
    initial begin
        $dumpfile("bitwise_and.vcd");
        $dumpvars(0, dut);
        A = 0;
        B = 1;
        repeat (16) begin
            #10;
            $display("t=%04d a=%b b=%b y=%b", $time, A, B, Y);
            A = A + 1;
        end
        $finish;
    end
endmodule

Lectures/lec10/bitwise_and.vcd
$date
	Fri Jan 26 15:18:56 2024
$end
$version
	Icarus Verilog
$end
$timescale
	1ns
$end
$scope module main $end
$scope module dut $end
$var wire 4 ! a [3:0] $end
$var wire 4 " b [3:0] $end
$var wire 4 # y [3:0] $end
$upscope $end
$upscope $end
$enddefinitions $end
#0
$dumpvars
b0 #
b1 "
b0 !
$end
#10
b1 #
b1 !
#20
b0 #
b10 !
#30
b1 #
b11 !
#40
b0 #
b100 !
#50
b1 #
b101 !
#60
b0 #
b110 !
#70
b1 #
b111 !
#80
b0 #
b1000 !
#90
b1 #
b1001 !
#100
b0 #
b1010 !
#110
b1 #
b1011 !
#120
b0 #
b1100 !
#130
b1 #
b1101 !
#140
b0 #
b1110 !
#150
b1 #
b1111 !
#160
b0 #
b0 !
