Lectures/lec10/gate_timing.v
`timescale 1ns / 1ns  // define the time units

module timing_g(output logic y, input logic a, b, c, d );
    wire n1, n2;

    and #2  g1(n1, a, b);
    or #3   g2(n2, n1, c);
    and #2  g3(y, n2, d);
endmodule

module main;
    logic a,b,c,d, y; 

    task apply_test(input [3:0] test_vec);
        begin
            {a,b,c,d} = test_vec;
            $display("d: t=%04d a=%b b=%b c=%b d=%b y=%b",
                $time, a, b, c, d, y);
            #10; // delay 10 units (10ns in this case)
        end
    endtask

    timing_g dut(y, a, b, c, d);

    initial begin
        $dumpfile("gate_timing.vcd");
        $dumpvars(0, dut);
        // trigged on change of monitored variable
        $monitor("m: t=%04d a=%b b=%b c=%b d=%b n1=%b n2=%b y=%b",
            $time, a, b, c, d, dut.n1, dut.n2, y);
        $display("first path setup");
        apply_test( 4'b1101 );
        $display("first path change");
        apply_test( 4'b0101 );
        #10;
        $display("second path setup");
        apply_test( 4'b1101 );
        $display("second path change");
        apply_test( 4'b1100 );

        $finish; // terminate the simulation
    end
endmodule

Lectures/lec10/dump.vcd
$date
	Mon Jan 31 10:08:21 2022
$end
$version
	Icarus Verilog
$end
$timescale
	1ns
$end
$scope module main $end
$var wire 1 ! y $end
$var reg 1 " a $end
$var reg 1 # b $end
$var reg 1 $ c $end
$var reg 1 % d $end
$scope module dut $end
$var wire 1 " a $end
$var wire 1 # b $end
$var wire 1 $ c $end
$var wire 1 % d $end
$var wire 1 & n1 $end
$var wire 1 ' n2 $end
$var wire 1 ! y $end
$upscope $end
$scope task apply_test $end
$var reg 4 ( test_vec [3:0] $end
$upscope $end
$upscope $end
$enddefinitions $end
#0
$dumpvars
b1101 (
x'
x&
1%
0$
1#
1"
x!
$end
#2
1&
#5
1'
#7
1!
#10
0"
b101 (
#12
0&
#15
0'
#17
0!
#30
1"
b1101 (
#32
1&
#35
1'
#37
1!
#40
0%
b1100 (
#42
0!
