Lectures/lec10/muxes2_1.v
module mux2_1_assign(output logic m, input logic a, b, sel);
    assign m = ~sel & a | sel & b;
endmodule

module mux_2_1_cond(output logic m, input logic a, b, sel);
    // b if sel is 1, otherwise a
    assign m = sel ? b : a;
    // this expression comes from C-language
endmodule

module mux_2_1_behave(output logic m, input logic a, b, sel);
    always_comb begin // a, b, sel trigger block
        if ( sel ) 
            m = b;
        else
            m = a;
    end
endmodule

Lectures/lec10/tb_muxes2_1.v
`timescale 1ns / 1ns

module main;
    logic  out; 
    logic a,b,sel;
    logic ma, mc, mb;
    integer all_ins; // 32 bit integer

    // instantiate the modules under test
    mux2_1_assign g1(ma, a, b, sel);
    mux_2_1_cond g2(mc, a, b, sel);
    mux_2_1_behave g3(mb, a, b, sel);

    assign {sel, a,b} = all_ins[2:0];

    initial begin
        $dumpfile("muxes2_1.vcd");
        $dumpvars(0, g1,g2,g3);
        for( all_ins = 0; all_ins <= 7; all_ins = all_ins + 1)
        begin
            #1; // delay after input change
            $display("sel=%b a=%b b=%b  ma=%b mc=%b mb=%b",
               sel, a, b, ma, mc, mb);
        end
        $finish;
    end
endmodule

Lectures/lec10/muxes2_1.vcd
$date
	Mon Sep 25 11:17:41 2023
$end
$version
	Icarus Verilog
$end
$timescale
	1ns
$end
$scope module main $end
$scope module g1 $end
$var wire 1 ! a $end
$var wire 1 " b $end
$var wire 1 # m $end
$var wire 1 $ sel $end
$upscope $end
$upscope $end
$scope module main $end
$scope module g2 $end
$var wire 1 ! a $end
$var wire 1 " b $end
$var wire 1 $ sel $end
$var wire 1 % m $end
$upscope $end
$upscope $end
$scope module main $end
$scope module g3 $end
$var wire 1 ! a $end
$var wire 1 " b $end
$var wire 1 $ sel $end
$var reg 1 & m $end
$upscope $end
$upscope $end
$enddefinitions $end
#0
$dumpvars
0&
0%
0$
0#
0"
0!
$end
#1
1"
#2
1#
1%
1&
0"
1!
#3
1"
#4
0#
0%
0&
0"
0!
1$
#5
1#
1%
1&
1"
#6
0#
0%
0&
0"
1!
#7
1#
1%
1&
1"
#8
0#
0%
0&
0"
0!
0$
