Lectures/lec10/sop_pos.v
`timescale 1ns / 1ns

module sop_pos(output logic y, z, input logic a, b, c);

    assign y = ~a & ~b & c | ~a & b & ~c | a & ~b & ~c | a & b & c;
    
    assign z = (~a | ~b | c) & (~a | b | ~c) & (a | ~b | ~c) & (a | b | c);

endmodule

module main;
    logic a, b, c, y;
    logic [2:0] bits;
    
    task apply_test(input [2:0] test_vec);
        begin
            {a, b, c} = test_vec;
            #10;
            $display("t=%04d vec=%03b y=%b z=%b", $time, test_vec, y, z);
        end
    endtask
    
    sop_pos testing(y, z, a, b, c);
    
    initial begin
        $dumpfile("sop_pos.vcd");
        $dumpvars(0, testing);
        bits = 0;
        repeat ( 8 ) begin
            apply_test( bits );
            bits = bits + 1;
        end
        $finish;
    end            
endmodule

Lectures/lec10/sop_pos.vcd
$date
	Mon Sep 25 12:16:28 2023
$end
$version
	Icarus Verilog
$end
$timescale
	1ns
$end
$scope module main $end
$scope module testing $end
$var wire 1 ! a $end
$var wire 1 " b $end
$var wire 1 # c $end
$var wire 1 $ y $end
$var wire 1 % z $end
$upscope $end
$upscope $end
$enddefinitions $end
#0
$dumpvars
0%
0$
0#
0"
0!
$end
#10
1$
1%
1#
#20
1%
1"
0#
#30
0$
0%
1#
#40
1$
1%
1!
0"
0#
#50
0%
0$
1#
#60
0%
0$
1"
0#
#70
1%
1$
1#
