Lectures/lec15/shift_reg_dff.v
module dff( output logic q, input logic d, clk);
    always_ff @(posedge clk) begin
        q <= d;
    end
endmodule

module shift_reg(
    output logic [2:0] sh,
    input logic sin, clk
);

    dff bit0( sh[0], sin, clk);
    dff bit1( sh[1], sh[0], clk);
    dff bit2( sh[2], sh[1], clk);
endmodule

Lectures/lec15/dff_tb.v
`timescale 1ns / 1ns
parameter delay = 2;

module main;
    logic q, d, clk;

    dff dut( q, d, clk );

    initial begin
        $monitor("t=%04d q=%b d=%b clk=%b",
            $time, q, d, clk); 
    end

    initial begin
        $dumpfile("dff.vcd");
        $dumpvars(0, main);
        d = 0; clk = 0; #5;
        d = 0; clk = 1; #5;
        d = 0; clk = 0; #5;
        d = 1; clk = 0; #5;
        d = 1; clk = 1; #5;
        d = 1; clk = 0; #5;
        d = 0; clk = 0; #5;
        d = 0; clk = 1; #5;
        d = 1; clk = 1; #5;
        d = 0; clk = 1; #5;
        $finish;
    end
endmodule

Lectures/lec15/dff.vcd
$date
	Fri Oct  6 11:13:44 2023
$end
$version
	Icarus Verilog
$end
$timescale
	1ns
$end
$scope module main $end
$var wire 1 ! q $end
$var reg 1 " clk $end
$var reg 1 # d $end
$scope module dut $end
$var wire 1 " clk $end
$var wire 1 # d $end
$var reg 1 ! q $end
$upscope $end
$upscope $end
$enddefinitions $end
#0
$dumpvars
0#
0"
x!
$end
#5
1"
#7
0!
#10
0"
#15
1#
#20
1"
#22
1!
#25
0"
#30
0#
#35
1"
#37
0!
#40
1#
#45
0#
