Lectures/lec15/seq4_v1.v
module nbit_dff #(parameter N=8) (
    output logic [N-1:0] q,
    input logic [N-1:0] d,
    input logic clk, reset );

    always_ff @(posedge clk) begin
        if ( reset ) begin
            q <= 0;
        end
        else begin
            q <= d;
        end
    end
endmodule

module seq4( output logic [1:0] cur,
             input logic clk, reset );
    logic [1:0] next;

    always_comb begin
        case(cur)
            2'b00: next = 2'b01;
            2'b01: next = 2'b11;
            2'b11: next = 2'b10;
            2'b10: next = 2'b00;
        endcase
    end

    nbit_dff #(2) st( cur, next, clk, reset);
endmodule

Lectures/lec15/nbit_dff_tb.v
parameter SIZE = 8;

module main;
    logic [SIZE-1:0] q, d;
    logic clk,reset;

    nbit_dff #(8) dut( q, d, clk, reset );

    task automatic load_data( logic [SIZE-1:0] din );
        d = din;
        clk = 0; #5; clk = 1; #5;
    endtask

    task automatic reset_reg;
        reset = 1; clk = 0;
        #5; clk = 1; #5;
        reset = 0;
    endtask

    initial begin
        $monitor("t=%04d q=%b d=%b clk=%b reset=%b",
            $time, q, d, clk, reset); 
    end

    initial begin
        $dumpfile("nbit_dff.vcd");
        $dumpvars(0, main);
        d = 8'hff; 
        reset_reg; // test rest
        #10; 
        load_data( 8'b01010101 ); // try loading a value
        load_data( 8'b10101010 ); // try a different value
        reset = 1;
        load_data( 8'b10101010 );// loading a value with reset
        reset = 0;
        load_data( 8'hab ); 
        $finish;
    end
endmodule

Lectures/lec15/nbit_dff.vcd
$date
	Fri Oct  6 12:43:04 2023
$end
$version
	Icarus Verilog
$end
$timescale
	1s
$end
$scope module main $end
$var wire 8 ! q [7:0] $end
$var reg 1 " clk $end
$var reg 8 # d [7:0] $end
$var reg 1 $ reset $end
$scope module dut $end
$var wire 1 " clk $end
$var wire 8 % d [7:0] $end
$var wire 1 $ reset $end
$var reg 8 & q [7:0] $end
$upscope $end
$scope task load_data $end
$upscope $end
$scope task reset_reg $end
$upscope $end
$upscope $end
$enddefinitions $end
#0
$dumpvars
bx &
b11111111 %
1$
b11111111 #
0"
bx !
$end
#5
b0 !
b0 &
1"
#10
0$
#20
0"
b1010101 #
b1010101 %
#25
b1010101 !
b1010101 &
1"
#30
0"
b10101010 #
b10101010 %
#35
b10101010 !
b10101010 &
1"
#40
0"
1$
#45
b0 !
b0 &
1"
#50
0"
b10101011 #
b10101011 %
0$
#55
b10101011 !
b10101011 &
1"
